{
    "Vend\u00e9g": {
        "ProfilePicturePath": "../resources/pictures/userDefault.png",
        "completedLessonInLearn": {
            "lesson1": 1,
            "lesson2": 1,
            "lesson3": 1,
            "lesson4": 1,
            "lesson5": 1,
            "lesson6": 1,
            "lesson7": 1,
            "lesson8": 1,
            "lesson9": 1,
            "lesson10": 1
        },
        "timeSpentInLearn": {
            "lesson1": 1,
            "lesson2": 1,
            "lesson3": 1,
            "lesson4": 1,
            "lesson5": 1,
            "lesson6": 1,
            "lesson7": 1,
            "lesson8": 1,
            "lesson9": 1,
            "lesson10": 1
        },
        "goodAnswersInLearn": {
            "lesson1": 1,
            "lesson2": 1,
            "lesson3": 1,
            "lesson4": 1,
            "lesson5": 1,
            "lesson6": 1,
            "lesson7": 1,
            "lesson8": 1,
            "lesson9": 1,
            "lesson10": 1
        },
        "LearnMessageShown": false,
        "LearnMedal": 1,
        "QuizMedal": 0,
        "EmailMedal": 0,
        "badge01": 1,
        "badge02": 1,
        "badge03": 0,
        "badge04": 0,
        "badge05": 0,
        "badge06": 0,
        "Score": 1350,
        "Theme": "default",
        "LearnMessageShow": false
    }
}